setup.py
t_datetime/__init__.py
t_datetime.egg-info/PKG-INFO
t_datetime.egg-info/SOURCES.txt
t_datetime.egg-info/dependency_links.txt
t_datetime.egg-info/top_level.txt
t_datetime.egg-info/zip-safe