Metadata-Version: 1.0
Name: t-datetime
Version: 0.1
Summary: T datetime library
Home-page: https://gitlab.com/ddmello/lib/python/t_datetime.git
Author: Darrin D'Mello
Author-email: darrin.dmello@gmail.com
License: MIT
Platform: UNKNOWN
